local_runner/__init__.py
local_runner/main.py
local_runner/comms/__init__.py
local_runner/comms/base.py
local_runner/comms/dtos.py
local_runner/comms/http_reporter.py
local_runner/comms/ws.py
local_runner/config/__init__.py
local_runner/config/config.py
local_runner/creds/__init__.py
local_runner/creds/creds.py
local_runner/exec/__init__.py
local_runner/exec/manager.py
local_runner/handler/__init__.py
local_runner/handler/censor.py
local_runner/handler/handler.py
local_runner/registration/__init__.py
local_runner/registration/registration.py
local_runner/tokens/__init__.py
local_runner/tokens/issuer.py
promptops/__init__.py
promptops/corrections.py
promptops/feedback.py
promptops/history.py
promptops/main.py
promptops/query.py
promptops/settings.py
promptops/settings_store.py
promptops/similarity.py
promptops/trace.py
promptops/ui.py
promptops/user.py
promptops/version.py
promptops/version_check.py
promptops/gitaware/__init__.py
promptops/gitaware/commits.py
promptops/gitaware/project.py
promptops/index/__init__.py
promptops/index/content.py
promptops/index/entry_point.py
promptops/index/index_store.py
promptops/loading/__init__.py
promptops/loading/base.py
promptops/loading/cancellable.py
promptops/loading/context.py
promptops/loading/multi.py
promptops/loading/pong.py
promptops/loading/progress.py
promptops/loading/promptops.py
promptops/loading/simple.py
promptops/query/__init__.py
promptops/query/dtos.py
promptops/query/explanation.py
promptops/query/git_repo.py
promptops/query/lookup.py
promptops/query/messages.py
promptops/query/query.py
promptops/query/suggest_next.py
promptops/recipes/__init__.py
promptops/recipes/creation.py
promptops/recipes/executor.py
promptops/recipes/run.py
promptops/recipes/terraform.py
promptops/scrub_secrets/__init__.py
promptops/scrub_secrets/scrub.py
promptops/secret/__init__.py
promptops/secret/scrub.py
promptops/shells/__init__.py
promptops/shells/base.py
promptops/shells/bash.py
promptops/shells/common.py
promptops-0.1.11.dist-info/LICENSE.txt
promptops-0.1.11.dist-info/METADATA
promptops-0.1.11.dist-info/WHEEL
promptops-0.1.11.dist-info/entry_points.txt
promptops-0.1.11.dist-info/top_level.txt
promptops-0.1.11.dist-info/RECORD
