Metadata-Version: 2.1
Name: promptops
Version: 0.1.11
Summary: Your CLI assistant. Ask questions, get shell commands.
Home-page: https://promptops.com/
Author: CtrlStack inc.
License: GPLv3
Project-URL: Documentation, https://docs.promptops.com/cli
Project-URL: Changelog, https://docs.promptops.com/en/stable/changelog.html
Project-URL: Live demo, https://promptops.com/
Classifier: License :: OSI Approved :: GNU General Public License v3 (GPLv3)
Classifier: Intended Audience :: Developers
Classifier: Intended Audience :: System Administrators
Requires-Python: >=3.9
License-File: LICENSE.txt
Requires-Dist: colorama (~=0.4.6)
Requires-Dist: requests (~=2.31.0)
Requires-Dist: websockets (~=11.0.3)
Requires-Dist: detect-secrets (~=1.4.0)
Requires-Dist: prompt-toolkit (~=3.0.38)
Requires-Dist: numpy (~=1.25.0)
Requires-Dist: pyperclip (~=1.8.2)
Requires-Dist: thefuzz (~=0.19.0)
Requires-Dist: psutil (~=5.9.5)
Requires-Dist: wcwidth (~=0.2.6)
Requires-Dist: boto3 (~=1.26.159)
Requires-Dist: kubernetes (~=26.1.0)
Requires-Dist: urllib3 (<2,>=1.26)
Requires-Dist: setuptools (~=68.0.0)
Requires-Dist: pip
